LICENSE
aio_nano/__init__.py
aio_nano/py.typed
aio_nano/rpc/__init__.py
aio_nano/rpc/client.py
aio_nano/rpc/models.py
aio_nano/ws/__init__.py
aio_nano/ws/client.py
aio_nano/ws/models.py
aio_nano-0.1.9.dist-info/LICENSE
aio_nano-0.1.9.dist-info/WHEEL
aio_nano-0.1.9.dist-info/METADATA
aio_nano-0.1.9.dist-info/RECORD
