Metadata-Version: 2.1
Name: aio-nano
Version: 0.1.9
Summary: An asynchronous nano currency library
Home-page: https://github.com/ogtega/aio-nano
License: MIT
Keywords: nano,currency,async,crypto,python
Author: Teslim Olunlade
Author-email: tolunlade@outlook.com
Requires-Python: >=3.10,<4.0
Classifier: License :: OSI Approved :: MIT License
Classifier: Programming Language :: Python :: 3
Classifier: Programming Language :: Python :: 3.10
Requires-Dist: aiohttp (>=3.8.1,<4.0.0)
Requires-Dist: pydantic (>=1.9.1,<2.0.0)
Requires-Dist: pytest-asyncio (>=0.19.0,<0.20.0)
Requires-Dist: websockets (>=10.3,<11.0)
Project-URL: Repository, https://github.com/ogtega/aio-nano
